Metadata-Version: 1.1
Name: Flask-Click-Migrate
Version: 0.1.0
Summary: A library to glue flask + alembic + click
Home-page: https://github.com/eatfirst/Flask-Click-Migrate
Author: EatFirst.com
Author-email: opensource@eatfirst.com
License: UNKNOWN
Platform: UNKNOWN
Classifier: Development Status :: 4 - Beta
Classifier: License :: OSI Approved :: MIT License
Classifier: Operating System :: OS Independent
Classifier: Programming Language :: Python :: 2.7
Classifier: Programming Language :: Python :: 3
Classifier: Programming Language :: Python :: 3.4
Classifier: Programming Language :: Python :: 3.5
Classifier: Programming Language :: Python :: 3.6
